{
  "entityType" : "NOTIFICATION_TARGET",
  "entity" : {
    "configuration" : {
      "type" : "PLATFORM_USERS",
      "description" : "If rule trigger is an action that affects some user (e.g. alarm assigned to user) - this user",
      "usersFilter" : {
        "type" : "AFFECTED_USER"
      }
    },
    "externalId" : null,
    "id" : {
      "entityType" : "NOTIFICATION_TARGET",
      "id" : "b4e5ce81-bd9d-11f0-9f62-dbf745488a54"
    },
    "name" : "Affected user"
  },
  "relations" : [ ],
  "attributes" : {
    "SERVER_SCOPE" : [ ]
  }
}